[
  {
    "type": "note",
    "event_id": "360_note",
    "title": "年度销售之星获奖感言要点",
    "content": "一、感谢：1. 感谢公司平台与领导郑总、王经理；2. 感谢同事刘志强、李雪等伙伴支持；3. 感谢家人理解。二、工作心得：1. 真诚服务客户；2. 持续学习专业知识；3. 团队协作。三、未来展望：继续努力，争取更大成绩。",
    "datetime": "2025-01-24 14:45:00",
    "related_event_ids": "360"
  },
  {
    "type": "note",
    "event_id": "362_note",
    "title": "额外提成记录与规划",
    "content": "一、喜讯：第四季度订单追加，获得额外提成1.5万元。二、发放时间：预计下月随工资发放。三、初步规划：1. 部分存入儿子教育基金；2. 部分用于家庭开支；3. 预留小部分作为家庭活动经费。",
    "datetime": "2025-01-24 20:30:00",
    "related_event_ids": "362"
  },
  {
    "type": "note",
    "event_id": "none",
    "title": "中级销售工程师备考知识点",
    "content": "一、客户关系管理：1. 长期客户维护策略；2. 客户满意度提升方法。二、销售心理学：1. 消费者决策过程；2. 价格谈判技巧。三、产品知识：最新手机型号参数对比。",
    "datetime": "2025-01-24 21:30:00",
    "related_event_ids": "无"
  },
  {
    "type": "note",
    "event_id": "1832",
    "title": "整理大客户签约材料待办清单",
    "content": "一、材料核对：1. 与李思远总最终确认的合同；2. 配置清单；3. 报价单电子版；二、材料准备：1. 打印、装订全套纸质材料；2. 分类整理；3. 附上所有前期沟通记录摘要",
    "datetime": "2025-04-30 08:45:00",
    "related_event_ids": "1832"
  },
  {
    "type": "note",
    "event_id": "1886_note",
    "title": "家庭郊游规划要点",
    "content": "一、目的地信息：1. 西青郊野公园；2. 确认开放时间与路线；二、物品清单核对：1. 野餐食物（已采购）；2. 饮用水、果汁；3. 防晒霜、驱蚊液；4. 孩子备用衣物；5. 露营垫、野餐篮（已放玄关）；三、出行前准备：1. 出发时间确认；2. 车辆加油提醒（车钥匙已放显眼处）",
    "datetime": "2025-05-04 15:10:00",
    "related_event_ids": "1886"
  },
  {
    "type": "note",
    "event_id": "none",
    "title": "《影响力》读书笔记要点",
    "content": "一、权威原则：1. 核心：人们倾向于服从权威；2. 应用：销售中展示专业认证、引用专家观点；二、稀缺原则：1. 核心：物以稀为贵；2. 应用：强调产品限量、限时优惠；三、工作结合思考：1. 与客户沟通时可适时引用行业报告数据（权威）；2. 推广新品时可强调首发或限量供应（稀缺）",
    "datetime": "2025-05-04 16:10:00",
    "related_event_ids": "无"
  },
  {
    "type": "note",
    "event_id": "2091_note",
    "title": "马拉松赛前准备清单",
    "content": "一、装备检查：1. 跑鞋、服装、号码布；2. 能量胶、盐丸、水壶；二、比赛策略：1. 前5公里稳心率；2. 后5公里酌情加速；3. 每5公里补给一次；三、其他事项：1. 与陈健在体育场北门集合；2. 确认手机电量充足",
    "datetime": "2025-05-16 20:10:00",
    "related_event_ids": "2091"
  },
  {
    "type": "note",
    "event_id": "none",
    "title": "重金属音乐讨论记录",
    "content": "一、乐队：锈蚀齿轮；二、讨论要点：1. 主唱嗓音的爆发力与颗粒感；2. 贝斯线在整体编曲中的驱动作用；3. 地下乐队商业化与独立精神的平衡；三、个人感想：贝斯编排是亮点，商业化讨论有启发",
    "datetime": "2025-05-16 22:15:00",
    "related_event_ids": "无"
  },
  {
    "type": "note",
    "event_id": "2082_note",
    "title": "晨会案例分享复盘",
    "content": "一、成功要点：1. 运用稀缺性原则（限量版预售）；2. 结合具体客户反馈与销售数据；3. 分享了有效销售话术；二、后续跟进：1. 将案例整理成文档；2. 思考社会认同原则的应用场景",
    "datetime": "2025-05-16 09:40:00",
    "related_event_ids": "2082"
  },
  {
    "type": "note",
    "event_id": "none",
    "title": "学生团购销售经验总结",
    "content": "一、成功要点：1. 提前了解学生专业需求（设计/编程）；2. 针对性推荐笔记本电脑和手机套餐；3. 详细演示产品性能；4. 核算团购折扣与分期方案；二、后续跟进：1. 提醒小赵整理单据；2. 可考虑建立学生客户群进行长期维护",
    "datetime": "2025-07-05 14:25:00",
    "related_event_ids": "2871"
  },
  {
    "type": "note",
    "event_id": "none",
    "title": "重金属音乐新专辑记录",
    "content": "一、专辑名称：The Sound of Perseverance；二、乐队：Death；三、推荐曲目：1. Spirit Crusher；2. Flesh and the Power It Serves；四、听后感：技术性强，鼓点密集，适合跑步时听",
    "datetime": "2025-07-05 20:00:00",
    "related_event_ids": "无"
  }
]