{
"年龄": ["18","19","20","21","22","23","24","25","26","27","28","29","30","31","32","33","34","35","36","37","38","39","40","41","42","43","44","45","46","47","48","49","50","51","52","53","54","55","56","57","58","59","60"],
  "住址": ["一线省会城市", "新一线城市", "二线城市", "三线城市", "四线及以下城市", "乡镇地区", "农村地区"],
"籍贯": ["北京市","天津市","上海市","重庆市","石家庄市","唐山市","秦皇岛市","邯郸市","邢台市","保定市","张家口市","承德市","沧州市","廊坊市","衡水市","太原市","大同市","阳泉市","长治市","晋城市","朔州市","晋中市","运城市","忻州市","临汾市","吕梁市","呼和浩特市","包头市","乌海市","赤峰市","通辽市","鄂尔多斯市","呼伦贝尔市","巴彦淖尔市","乌兰察布市","沈阳市","大连市","鞍山市","抚顺市","本溪市","丹东市","锦州市","营口市","阜新市","辽阳市","盘锦市","铁岭市","朝阳市","葫芦岛市","长春市","吉林市","四平市","辽源市","通化市","白山市","松原市","白城市","哈尔滨市","齐齐哈尔市","鸡西市","鹤岗市","双鸭山市","大庆市","伊春市","佳木斯市","七台河市","牡丹江市","黑河市","绥化市","南京市","无锡市","徐州市","常州市","苏州市","南通市","连云港市","淮安市","盐城市","扬州市","镇江市","泰州市","宿迁市","杭州市","宁波市","温州市","嘉兴市","湖州市","绍兴市","金华市","衢州市","舟山市","台州市","丽水市","合肥市","芜湖市","蚌埠市","淮南市","马鞍山市","淮北市","铜陵市","安庆市","黄山市","滁州市","阜阳市","宿州市","六安市","亳州市","池州市","宣城市","福州市","厦门市","莆田市","三明市","泉州市","漳州市","南平市","龙岩市","宁德市","南昌市","景德镇市","萍乡市","九江市","新余市","鹰潭市","赣州市","吉安市","宜春市","抚州市","上饶市","济南市","青岛市","淄博市","枣庄市","东营市","烟台市","潍坊市","济宁市","泰安市","威海市","日照市","临沂市","德州市","聊城市","滨州市","菏泽市","郑州市","开封市","洛阳市","平顶山市","安阳市","鹤壁市","新乡市","焦作市","濮阳市","许昌市","漯河市","三门峡市","南阳市","商丘市","信阳市","周口市","驻马店市","武汉市","黄石市","十堰市","宜昌市","襄阳市","鄂州市","荆门市","孝感市","荆州市","黄冈市","咸宁市","随州市","长沙市","株洲市","湘潭市","衡阳市","邵阳市","岳阳市","常德市","张家界市","益阳市","郴州市","永州市","怀化市","娄底市","广州市","韶关市","深圳市","珠海市","汕头市","佛山市","江门市","湛江市","茂名市","肇庆市","惠州市","梅州市","汕尾市","河源市","阳江市","清远市","东莞市","中山市","潮州市","揭阳市","云浮市","南宁市","柳州市","桂林市","梧州市","北海市","防城港市","钦州市","贵港市","玉林市","百色市","贺州市","河池市","来宾市","崇左市","海口市","三亚市","三沙市","儋州市","成都市","自贡市","攀枝花市","泸州市","德阳市","绵阳市","广元市","遂宁市","内江市","乐山市","南充市","眉山市","宜宾市","广安市","达州市","雅安市","巴中市","资阳市","贵阳市","六盘水市","遵义市","安顺市","毕节市","铜仁市","昆明市","曲靖市","玉溪市","保山市","昭通市","丽江市","普洱市","临沧市","拉萨市","日喀则市","昌都市","林芝市","山南市","那曲市","西安市","铜川市","宝鸡市","咸阳市","渭南市","延安市","汉中市","榆林市","安康市","商洛市","兰州市","嘉峪关市","金昌市","白银市","天水市","武威市","张掖市","平凉市","酒泉市","庆阳市","定西市","陇南市","西宁市","海东市","银川市","石嘴山市","吴忠市","固原市","中卫市","乌鲁木齐市","克拉玛依市","吐鲁番市","哈密市"],
"职业": ["中国共产党中央委员会和地方各级党组织负责人","国家权力机关及其工作机构负责人","人民法院负责人","人民检察院负责人","国家行政机关及其工作机构负责人","民主党派负责人","工会负责人","共青团负责人","妇女联合会负责人","群众自治组织负责人","高等学校校长","中小学校校长","卫生单位负责人","科研单位负责人","企业董事","企业经理","企业职能部门经理或主管","哲学研究人员","经济学研究人员","法学研究人员","社会学研究人员","教育科学研究人员","文学艺术研究人员","历史学研究人员","数学研究人员","物理学研究人员","化学研究人员","天文学研究人员","地球科学研究人员","生物科学研究人员","医学研究人员","地质勘探工程技术人员","大地测量工程技术人员","采矿工程技术人员","石油开采工程技术人员","冶炼工程技术人员","化工实验工程技术人员","机械设计工程技术人员","仪器仪表工程技术人员","飞机设计工程技术人员","航天工程技术人员","电子元器件工程技术人员","通信工程技术人员","计算机软件技术人员","电机与电器工程技术人员","发电工程技术人员","汽车运用工程技术人员","船舶运用工程技术人员","民用航空维修与适航专业技术人员","铁道运输工程技术人员","建筑设计工程技术人员","水利水电建筑工程技术人员","林业生态环境工程技术人员","水资源工程技术人员","水产养殖工程技术人员","纺纱工程技术人员","食品工程技术人员","气象观测人员","地震工程技术人员","环境监测工程技术人员","安全工程技术人员","标准化工程技术人员","计量工程技术人员","质量工程技术人员","土壤肥料技术人员","植物保护技术人员","兽医","畜牧技术人员","飞行驾驶员","内科医师","外科医师","儿科医师","妇产科医师","中医内科医师","中医外科医师","中西医结合医师","护士","助产士","经济计划人员","统计人员","会计人员","审计人员","银行信贷员","保险推销员","证券交易员","法官","检察官","律师","公证员","高等教育教师","中学教师","小学教师","幼儿教师","文学作家","电影电视导演","电影电视演员","歌唱演员","民族乐器演奏员","画家","书法家","服装设计人员","室内装饰设计人员","广告设计人员","教练员","裁判员","运动员","文字记者","文字编辑","播音员","节目主持人","翻译","图书资料业务人员","档案业务人员","考古工作者","文物鉴定和保管人员", "环卫工（保洁员）","餐馆老板（个体工商户）","厨师（中式烹调师）","超市老板（个体工商户）","便利店老板（个体工商户）","理发店老板（个体工商户）","美容店老板（个体工商户）","汽修店老板（个体工商户）","早餐店老板（个体工商户）","水果店老板（个体工商户）","蔬菜店老板（个体工商户）","药店老板（个体工商户）","服装店老板（个体工商户）","小吃店老板（个体工商户）","奶茶店老板（个体工商户）","面包店老板（个体工商户，对应烘焙相关）","干洗店老板（个体工商户，对应洗衣师）","家电维修店老板（个体工商户，对应家用电器产品维修工）","手机维修店老板（个体工商户，对应通信设备维修相关）","杂货店老板（个体工商户）","退休人员", "无业"],
"学历": ["小学及以下", "初中", "高中 / 中专", "大专", "本科", "硕士", "博士及以上"],
"常用联系方式": ["邮箱", "电话", "QQ", "微信", "社交平台"],
"体型": ["偏瘦", "标准", "微胖", "肥胖", "健壮"],
"健康状况": ["良好（无基础病）", "一般（偶有小病痛）", "较差（有慢性基础病）", "极差（需长期治疗 / 护理）"],
"收入": ["3000 元以下", "3001-5000 元", "5001-8000 元", "8001-12000 元", "12001-20000 元", "20001-50000 元", "50001 元以上"],
"婚姻": ["未婚", "已婚", "离异", "丧偶", "同居"],
"兴趣": ["读书（小说 / 历史 / 散文）","弹吉他","跑步（晨跑 / 夜跑）","追剧（国产剧 / 美剧 / 韩剧）","玩手游（王者荣耀 / 原神）","听音乐（流行 / 古典 / 摇滚）","烹饪（家常菜 / 川菜 / 粤菜）","旅行（国内游 / 境外游 / 自驾游）","摄影（风景 / 人像 / 街拍）","手工折纸（千纸鹤 / 复杂折纸）","养宠物（猫 / 狗 / 仓鼠 / 金鱼）","美妆护肤（日常护肤 / 彩妆）","瑜伽（初级 / 进阶 / 空中瑜伽）","看电影（院线片 / 经典老片）","打羽毛球（单打 / 双打）","画画（水彩 / 素描 / 油画）","钓鱼（淡水钓 / 海钓）","烘焙（蛋糕 / 饼干 / 面包）","骑行（城市骑行 / 短途骑行）","收藏邮票（普通邮票 / 纪念邮票）","学外语（英语 / 日语 / 法语）","弹钢琴（古典 / 流行）","跳广场舞（经典舞曲 / 流行舞曲）","玩桌游（狼人杀 / 三国杀）","种花种草（月季 / 多肉 / 绿萝）","写日记（纸质 / 电子）","打乒乓球（单打 / 双打）","看动漫（日本 / 国产）","做手账（装饰 / 记录）","养多肉（普通 / 稀有品种）","健身撸铁（力量训练 / 减脂）","听播客（知识 / 娱乐类）","打网球（单打 / 双打）","雕刻（木雕 / 橡皮章）","露营（公园 / 野外）","收藏手办（动漫 / 游戏）","练书法（楷书 / 行书）","跳街舞（breaking/hip-hop）","玩端游（英雄联盟 / 绝地求生）","做陶艺（拉坯 / 捏塑）","看脱口秀（线下 / 线上）","打排球（室内 / 沙滩）","学编程（Python/Java）","徒步登山（短途 / 高山）","收藏古币（古代 / 近代）","练普拉提（垫上 / 器械）","看纪录片（自然 / 历史）","打台球（斯诺克 / 美式八球）","做美甲（纯色 / 款式）","放风筝（传统 / 卡通）","收藏明信片（风景 / 主题）","学插花（日式 / 西式）","弹尤克里里（指弹 / 弹唱）","跳爵士舞（power / 性感）","玩卡牌（Pokemon / 斗地主）","做烘焙面包（吐司 / 欧包）","看相声（传统 / 新派）","打保龄球（单人 / 组队）","学剪辑（剪映 / Pr）","溯溪（休闲 / 探险）","收藏漫画书（少年 / 少女）","练太极（陈氏 / 杨氏）","听戏曲（京剧 / 越剧）","打毽子（单人 / 多人）","做羊毛毡（戳戳乐 / 湿毡）","观星（肉眼 / 望远镜）","收藏纪念币（生肖 / 事件）","学化妆（日常 / 舞台）","弹古筝（传统 / 现代）","跳民族舞（傣族 / 藏族）","玩密室逃脱（恐怖 / 解谜）","做果酱（草莓 / 蓝莓）","看综艺（真人秀 / 竞技）","打橄榄球（美式 / 英式）","学插画（商业 / 儿童）","攀岩（室内 / 室外）","收藏酒瓶（白酒 / 红酒）","练芭蕾（基础 / 足尖）","听有声书（小说 / 知识）","打棒球（标准 / 软式）","做手工皂（冷制 / 热制）","骑行远游（跨省 / 短途）","收藏老照片（个人 / 历史）","学陶艺拉坯（基础 / 复杂）","弹琵琶（传统 / 现代）","跳肚皮舞（东方 / 部落）","玩剧本杀（情感 / 推理）","做泡菜（韩式 / 中式）","看科幻小说（硬 / 软科幻）","野钓（水库 / 河流）","练巴西柔术（基础 / 进阶）","听重金属（传统 / 激流）","打壁球（单人 / 双人）","学做汉服（裁剪 / 缝制）","滑雪（双板 / 单板）","收藏潮玩盲盒（泡泡玛特 / 其他）","学茶艺（绿茶 / 红茶）","玩轮滑（休闲 / 花样）","做手工编织（毛衣 / 围巾）","看历史小说（古代 / 近代）"],
"习惯": ["早睡早起", "晚睡晚起", "每日运动", "经常外卖", "定期阅读", "频繁刷社交媒体", "吸烟", "饮酒", "规律三餐", "熬夜","每周 3-5 次运动（跑步 / 健身）","每月 2-3 次外卖聚餐","每周 1 次超市采购囤货","每月 1 次家庭大扫除","每周 2 次阅读（书籍 / 杂志）","每季度 1 次体检","每月 2 次户外出行（徒步 / 露营）","每周 3 次自制餐食","每两周 1 次衣物换季整理","每月 1 次社交聚会（朋友 / 同事）","每周 1 次财务记账","每季度 2 次技能学习（线上 / 线下）","每月 1 次长辈探望","每周 2 次亲子互动（出游 / 手工）","每季度 1 次旅行规划（短途 / 长途）","每月 2 次兴趣培养（绘画 / 乐器）","每周 3 次规律作息（固定睡起时间）","每季度 1 次家居焕新（软装调整）","每月 1 次健康饮食调整（减脂 / 养生）","每周 1 次运动复盘（效果 / 计划）","每季度 2 次知识复盘（笔记 / 总结）","每月 1 次公益活动（志愿 / 捐赠）","每周 2 次家庭聚餐","每季度 1 次职业规划梳理","每周 1 次社交平台断更（数字 detox）","每月 2 次厨艺尝试（新菜品学习）","每季度 1 次整理","每月 1 次家庭财务复盘（收支 / 储蓄）"],
"需求": ["日常购物需求", "学习提升需求", "职业发展需求", "健康管理需求", "社交互动需求", "娱乐放松需求", "家庭服务需求", "投资理财需求","亲密关系需求","兴趣爱好需求","风险保障需求"],
"人格": ["ISTJ（检查员型）","ISFJ（守护者型）","INFJ（咨询师型）","INTJ（战略家型）","ISTP（手艺人型）","ISFP（艺术家型）","INFP（调停者型）","INTP（逻辑学家型）","ESTP（企业家型）","ESFP（表演者型）","ENFP（活动家型）","ENTP（辩论家型）","ESTJ（总经理型）","ESFJ（执政官型）","ENFJ（教育家型）","ENTJ（指挥官型）"],
"价值观": ["家庭导向", "事业导向", "个人成长导向", "物质追求导向", "精神满足导向", "社会责任导向", "自由至上导向","自我超越","仁慈","普世主义","成就","权力","自主独立","刺激","保守稳定","安全","传统"],
"技能": ["电工","烹饪","编程（Python/Java）","汽车维修","Photoshop 图像处理","视频剪辑（Pr / 剪映）","会计做账","外语翻译（英语 / 日语）","家具组装","家电维修（冰箱 / 空调）","平面设计（AI/CDR）","网页制作（HTML/CSS）","手机维修","摄影构图与后期","书法创作（楷书 / 行书）","绘画（水彩 / 素描）","手工陶艺制作","插花艺术","茶艺冲泡（绿茶 / 红茶）","烘焙甜点（蛋糕 / 面包）","美甲设计","化妆造型（日常 / 舞台）","发型设计","瑜伽教学（初级 / 进阶）","健身教练指导","舞蹈编排（街舞 / 民族舞）","乐器演奏（钢琴 / 古筝）","声乐演唱","文案写作（广告 / 散文）","新闻采编","SEO 优化","新媒体运营（微信 / 抖音）","电商运营（淘宝 / 京东）","直播带货技巧","心理咨询基础","法律咨询（民事 / 合同）","导游讲解（国内 / 境外）","物流调度","仓储管理","叉车驾驶","电焊操作","木工制作","金属雕刻","刺绣（苏绣 / 十字绣）","剪纸艺术","篆刻印章","园艺养护（花卉 / 绿植）","宠物美容","婴幼儿护理","老人陪护","急救技能（CPR / 止血）","验光配镜","配镜加工","室内设计","软装搭配","CAD 制图","3D 建模（Blender/Maya）","无人机操控","智能家居调试","外语口语教学（英语 / 小语种）"],
"宗教信仰": ["无宗教信仰", "佛教", "基督教", "伊斯兰教", "道教", "天主教", "其他宗教"],
  "纪念日期": ["生日（个人 / 家人 / 伴侣）","纪念日（恋爱 / 结婚 / 订婚）","毕业日（小学 / 中学 / 大学 / 研究生）","元旦（1 月 1 日）","春节（农历正月初一）","元宵节（农历正月十五）","清明节（公历 4 月 5 日前后）","劳动节（5 月 1 日）","端午节（农历五月初五）","七夕节（农历七月初七）","中秋节（农历八月十五）","国庆节（10 月 1 日）","重阳节（农历九月初九）","冬至（公历 12 月 22 日前后）","入职日（首份工作 / 重要职业起点）","乔迁日（新家入住）","初次见面日（与挚友 / 伴侣第一次相遇）","子女出生日","父母生日","长辈寿辰（如 60 岁 / 80 岁等重要寿宴）","重要考试通过日（如高考录取日 / 职业资格证获取日）","好友重逢日（久别重逢的重要日子）","重大疾病康复日","旅行出发日（如第一次独自旅行 / 蜜月旅行）"],
  "目标规划": ["短期健康目标（如 1 个月减重 5 斤、每周运动 3 次）","长期职业目标（如 3 年内晋升部门主管、5 年掌握行业核心技能）","短期学习目标（如 1 季度学会基础 Python、半年通过英语四六级）","长期教育目标（如 5 年内考取硕士学历、10 年获得行业认证证书）","短期财务目标（如 3 个月存 1 万元应急资金、半年还清信用卡账单）","长期财务目标（如 5 年攒够首付、10 年实现被动收入覆盖生活开支）","短期家庭目标（如 1 个月内组织家庭旅行、半年陪父母体检 1 次）","长期家庭目标（如 3 年改善居住环境、5 年规划子女教育方案）","短期兴趣目标（如 2 个月学会弹唱 3 首吉他曲、1 季度完成 10 幅水彩画）","长期兴趣目标（如 2 年举办个人手作展、5 年成为某兴趣社群核心成员）","短期社交目标（如 1 个月认识 3 位行业同行、半年组织 2 次好友聚会）","长期社交目标（如 3 年建立稳定的职业人脉圈、5 年参与公益组织核心工作）","短期生活目标（如 1 个月养成规律作息、3 个月学会 5 道家常菜）","长期生活目标（如 2 年掌握家庭收纳系统、5 年打造理想家居环境）","短期自我提升目标（如 1 季度读 10 本专业书、半年提升公开演讲能力）","长期自我提升目标（如 3 年培养 2 项跨领域技能、5 年形成个人知识体系）","短期健康管理目标（如 2 个月改善睡眠质量、3 个月降低体脂率 2%）","长期健康管理目标（如 5 年保持每年体检、10 年养成终身运动习惯）","短期旅行目标（如半年内完成 1 次国内深度游、1 年体验 1 次小众旅行地）","长期旅行目标（如 3 年走遍国内 5 个省份、5 年实现 1 次境外自驾游）"],
  "社交关系": ["敌人","父亲","学生","合作","情人","朋友","丈夫","祖先","姐姐","妻子","同门","弟弟","女儿","儿子","哥哥","家人","老师","母亲","下属","同学","继任者","偶像","妹妹"]
}